ga4gh/vrsatile/pydantic/__init__.py
ga4gh/vrsatile/pydantic/version.py
ga4gh/vrsatile/pydantic/vrs_models.py
ga4gh/vrsatile/pydantic/vrsatile_models.py
ga4gh.vrsatile.pydantic-0.2.0.dist-info/LICENSE
ga4gh.vrsatile.pydantic-0.2.0.dist-info/METADATA
ga4gh.vrsatile.pydantic-0.2.0.dist-info/WHEEL
ga4gh.vrsatile.pydantic-0.2.0.dist-info/top_level.txt
ga4gh.vrsatile.pydantic-0.2.0.dist-info/RECORD
