Metadata-Version: 2.1
Name: ga4gh.vrsatile.pydantic
Version: 0.2.0
Summary: "Translation of the GA4GH VRS and VRSATILE Schemas to a Pydantic data model"
Home-page: https://github.com/ga4gh/vrs-pydantic
Author: Alex H. Wagner
Author-email: alex.wagner@nationwidechildrens.org
Keywords: bioinformatics,ga4gh,genomics,hgvs,spdi,variation
Classifier: Development Status :: 3 - Alpha
Classifier: Intended Audience :: Developers
Classifier: Intended Audience :: Healthcare Industry
Classifier: Intended Audience :: Science/Research
Classifier: License :: OSI Approved :: Apache Software License
Classifier: Operating System :: OS Independent
Classifier: Programming Language :: Python
Classifier: Programming Language :: Python :: 3
Classifier: Programming Language :: Python :: 3.8
Classifier: Topic :: Scientific/Engineering :: Bio-Informatics
Classifier: Topic :: Scientific/Engineering :: Medical Science Apps.
Requires-Python: >=3.8
License-File: LICENSE
Requires-Dist: pydantic ~=2.4.2
